labelCloud/__init__.py
labelCloud/__main__.py
labelCloud/control/__init__.py
labelCloud/control/alignmode.py
labelCloud/control/bbox_controller.py
labelCloud/control/config_manager.py
labelCloud/control/controller.py
labelCloud/control/drawing_manager.py
labelCloud/control/label_manager.py
labelCloud/control/pcd_manager.py
labelCloud/definitions/__init__.py
labelCloud/definitions/bbox.py
labelCloud/definitions/colors.py
labelCloud/definitions/context.py
labelCloud/definitions/labeling_mode.py
labelCloud/definitions/mode.py
labelCloud/definitions/types.py
labelCloud/definitions/label_formats/__init__.py
labelCloud/definitions/label_formats/base.py
labelCloud/definitions/label_formats/object_detection.py
labelCloud/definitions/label_formats/semantic_segmentation.py
labelCloud/io/__init__.py
labelCloud/io/labels/__init__.py
labelCloud/io/labels/base.py
labelCloud/io/labels/centroid.py
labelCloud/io/labels/config.py
labelCloud/io/labels/exceptions.py
labelCloud/io/labels/kitti.py
labelCloud/io/labels/vertices.py
labelCloud/io/pointclouds/__init__.py
labelCloud/io/pointclouds/base.py
labelCloud/io/pointclouds/numpy.py
labelCloud/io/pointclouds/open3d.py
labelCloud/io/segmentations/__init__.py
labelCloud/io/segmentations/base.py
labelCloud/io/segmentations/numpy.py
labelCloud/labeling_strategies/__init__.py
labelCloud/labeling_strategies/base.py
labelCloud/labeling_strategies/picking.py
labelCloud/labeling_strategies/spanning.py
labelCloud/model/__init__.py
labelCloud/model/bbox.py
labelCloud/model/perspective.py
labelCloud/model/point_cloud.py
labelCloud/resources/__init__.py
labelCloud/resources/default_classes.json
labelCloud/resources/default_config.ini
labelCloud/resources/labelCloud_icon.pcd
labelCloud/resources/rocket-palette.txt
labelCloud/resources/examples/__init__.py
labelCloud/resources/examples/exemplary.json
labelCloud/resources/examples/exemplary.ply
labelCloud/resources/icons/ICON_LICENSES.txt
labelCloud/resources/icons/__init__.py
labelCloud-1.1.1.dist-info/LICENSE
labelCloud-1.1.1.dist-info/METADATA
labelCloud-1.1.1.dist-info/WHEEL
labelCloud-1.1.1.dist-info/entry_points.txt
labelCloud-1.1.1.dist-info/top_level.txt
labelCloud-1.1.1.dist-info/RECORD
