Metadata-Version: 2.1
Name: labelCloud
Version: 1.1.1
Summary: A lightweight tool for labeling 3D bounding boxes in point clouds.
Home-page: https://github.com/ch-sa/labelCloud
Maintainer: Christoph Sager
Maintainer-email: christoph.sager@gmail.com
License: GNU General Public License v3.0
Keywords: labelCloud,machine learning,computer vision,annotation tool,labeling,point clouds,bounding boxes,3d object detection,6d pose estimation
Classifier: Development Status :: 4 - Beta
Classifier: Natural Language :: English
Classifier: Programming Language :: Python :: 3
Classifier: Programming Language :: Python :: 3.7
Classifier: Programming Language :: Python :: 3.8
Classifier: Programming Language :: Python :: 3.9
Classifier: License :: OSI Approved :: GNU General Public License v3 or later (GPLv3+)
Classifier: Topic :: Scientific/Engineering :: Artificial Intelligence
Classifier: Topic :: Multimedia :: Graphics :: Viewers
Requires-Python: >=3.7
License-File: LICENSE
Requires-Dist: numpy<2.0.0,>1.20.0
Requires-Dist: open3d
Requires-Dist: PyOpenGL
Requires-Dist: PyOpenGL-accelerate
Requires-Dist: PyQt5>=5.15.7
Provides-Extra: tests
Requires-Dist: pytest; extra == "tests"
Requires-Dist: pytest-qt; extra == "tests"
